mplus/__init__.py
mplus/imported/__init__.py
mplus/imported/bs4_dammit.py
mplus/moduls/__init__.py
mplus/moduls/requests.py
mplus/moduls/response.py
mplus/utils/__init__.py
mplus/utils/request.py
mplus-0.1.2.dist-info/METADATA
mplus-0.1.2.dist-info/WHEEL
mplus-0.1.2.dist-info/top_level.txt
mplus-0.1.2.dist-info/RECORD
