Metadata-Version: 2.1
Name: mplus
Version: 0.1.2
Summary: extensions
Home-page: https://github.com/gitduk/mplus
Author: kaige
Author-email: wdkany@gmail.com
License: MIT
Platform: UNKNOWN
Classifier: License :: OSI Approved :: MIT License
Classifier: Programming Language :: Python
Classifier: Programming Language :: Python :: 3
Classifier: Programming Language :: Python :: 3.6
Classifier: Programming Language :: Python :: Implementation :: CPython
Classifier: Programming Language :: Python :: Implementation :: PyPy
Requires-Python: >=3.6.0
Requires-Dist: requests
Requires-Dist: parsel
Requires-Dist: pymysql
Requires-Dist: lxml
Requires-Dist: w3lib
